lemonade_arcade/__init__.py
lemonade_arcade/arcade_games.py
lemonade_arcade/cli.py
lemonade_arcade/game_launcher.py
lemonade_arcade/game_orchestrator.py
lemonade_arcade/lemonade_client.py
lemonade_arcade/llm_service.py
lemonade_arcade/main.py
lemonade_arcade/utils.py
lemonade_arcade/version.py
lemonade_arcade/builtin_games/__init__.py
lemonade_arcade/builtin_games/rainbow_space_invaders.py
lemonade_arcade/builtin_games/snake_moving_food.py
lemonade_arcade/static/app.js
lemonade_arcade/static/favicon.ico
lemonade_arcade/static/style.css
lemonade_arcade/templates/index.html
lemonade_arcade-0.1.7.dist-info/licenses/LICENSE
lemonade_arcade-0.1.7.dist-info/METADATA
lemonade_arcade-0.1.7.dist-info/WHEEL
lemonade_arcade-0.1.7.dist-info/entry_points.txt
lemonade_arcade-0.1.7.dist-info/top_level.txt
lemonade_arcade-0.1.7.dist-info/RECORD
